poetry2setup.py
poetry2setup-1.1.0.dist-info/entry_points.txt
poetry2setup-1.1.0.dist-info/LICENSE
poetry2setup-1.1.0.dist-info/WHEEL
poetry2setup-1.1.0.dist-info/METADATA
poetry2setup-1.1.0.dist-info/RECORD
