Metadata-Version: 2.1
Name: poetry2setup
Version: 1.1.0
Summary: Convert python-poetry to setup.py
License: MIT
Author: abersheeran
Author-email: me@abersheeran.com
Requires-Python: >=3.6,<4.0
Classifier: License :: OSI Approved :: MIT License
Classifier: Programming Language :: Python :: 3
Classifier: Programming Language :: Python :: 3.10
Classifier: Programming Language :: Python :: 3.6
Classifier: Programming Language :: Python :: 3.7
Classifier: Programming Language :: Python :: 3.8
Classifier: Programming Language :: Python :: 3.9
Requires-Dist: poetry-core (>=1.0.0,<2.0.0)
